candorflow/__init__.py
candorflow/demo.py
candorflow/lambda_metric.py
candorflow/stability_controller.py
candorflow/utils.py
candorflow/version.py
candorflow-0.1.2.dist-info/licenses/LICENSE
candorflow-0.1.2.dist-info/METADATA
candorflow-0.1.2.dist-info/WHEEL
candorflow-0.1.2.dist-info/top_level.txt
candorflow-0.1.2.dist-info/RECORD
