Metadata-Version: 2.4
Name: candorflow
Version: 0.1.2
Summary: Training stability tools for synthetic demo
Author-email: Matt Gehring <matt@candorprotocol.com>
Requires-Python: >=3.8
License-File: LICENSE
Requires-Dist: torch
Requires-Dist: matplotlib
Requires-Dist: numpy
Dynamic: license-file
